pyspark_ai/__init__.py
pyspark_ai/ai_utils.py
pyspark_ai/cache.py
pyspark_ai/code_logger.py
pyspark_ai/file_cache.py
pyspark_ai/llm_chain_with_cache.py
pyspark_ai/prompt.py
pyspark_ai/pyspark_ai.py
pyspark_ai/python_executor.py
pyspark_ai/react_spark_sql_agent.py
pyspark_ai/search_tool_with_cache.py
pyspark_ai/spark_sql_chain.py
pyspark_ai/spark_utils.py
pyspark_ai/temp_view_utils.py
pyspark_ai/tool.py
pyspark_ai-0.1.20.dist-info/LICENSE
pyspark_ai-0.1.20.dist-info/METADATA
pyspark_ai-0.1.20.dist-info/WHEEL
pyspark_ai-0.1.20.dist-info/RECORD
