Metadata-Version: 2.1
Name: pyspark-ai
Version: 0.1.20
Summary: English SDK for Apache Spark
Home-page: https://github.com/databrickslabs/pyspark-ai
License: Apache-2.0
Author: Gengliang Wang
Author-email: gengliang@apache.org
Requires-Python: >=3.8.1,<4.0.0
Classifier: Development Status :: 3 - Alpha
Classifier: Intended Audience :: Developers
Classifier: License :: OSI Approved :: Apache Software License
Classifier: Programming Language :: Python :: 3
Classifier: Programming Language :: Python :: 3.9
Classifier: Programming Language :: Python :: 3.10
Classifier: Programming Language :: Python :: 3.11
Classifier: Programming Language :: Python :: 3.8
Provides-Extra: all
Provides-Extra: ingestion
Provides-Extra: plot
Provides-Extra: spark-connect
Provides-Extra: vector-search
Requires-Dist: beautifulsoup4 (>=4.12.2,<5.0.0) ; extra == "ingestion" or extra == "all"
Requires-Dist: faiss-cpu (>=1.7.4,<2.0.0) ; extra == "vector-search" or extra == "all"
Requires-Dist: google-api-python-client (>=2.90.0,<3.0.0) ; extra == "ingestion" or extra == "all"
Requires-Dist: grpcio (>=1.56.0) ; extra == "spark-connect" or extra == "all"
Requires-Dist: grpcio-status (>=1.56.0) ; extra == "spark-connect" or extra == "all"
Requires-Dist: langchain (>=0.0.353,<0.1.0)
Requires-Dist: openai (>=0.27.8,<0.28.0)
Requires-Dist: pandas (>=1.0.5) ; extra == "plot" or extra == "all"
Requires-Dist: plotly (>=5.15.0,<6.0.0) ; extra == "plot" or extra == "all"
Requires-Dist: pyarrow (>=4.0.0) ; extra == "plot" or extra == "all"
Requires-Dist: pydantic (>=1.10.10,<2.0.0)
Requires-Dist: pygments (>=2.15.1,<3.0.0)
Requires-Dist: requests (>=2.31.0,<3.0.0) ; extra == "ingestion" or extra == "all"
Requires-Dist: sentence-transformers (>=2.2.2,<3.0.0) ; extra == "vector-search" or extra == "all"
Requires-Dist: tiktoken (==0.4.0) ; extra == "ingestion" or extra == "all"
Requires-Dist: torch (>=2.0.0,!=2.0.1,!=2.1.0) ; extra == "vector-search" or extra == "all"
